{"1": [[{"type": "kill", "data": {"actor": {"position": {"x": -1912, "y": -35, "z": 128}, "ingameTeam": "CT", "playerId": "flusha"}, "victim": {"position": {"x": -1018, "y": -247, "z": 162}, "ingameTeam": "TERRORIST", "playerId": "NiKo"}, "weapon": "usp_silencer", "headshot": false, "penetrated": false}, "roundIdx": 1, "date": "2018-03-04T19:24:39.857+00:00"}], [{"type": "kill", "data": {"actor": {"position": {"x": -1960, "y": -950, "z": 128}, "ingameTeam": "TERRORIST", "playerId": "GuardiaN"}, "victim": {"position": {"x": -1890, "y": -1195, "z": 302}, "ingameTeam": "CT", "playerId": "Lekr0"}, "weapon": "glock", "headshot": false, "penetrated": false}, "roundIdx": 1, "date": "2018-03-04T19:24:27.178+00:00"}], [{"type": "kill", "data": {"actor": {"position": {"x": -869, "y": -253, "z": 96}, "ingameTeam": "TERRORIST", "playerId": "olofmeister"}, "victim": {"position": {"x": -1775, "y": -94, "z": 192}, "ingameTeam": "CT", "playerId": "flusha"}, "weapon": "glock", "headshot": false, "penetrated": false}, "roundIdx": 1, "date": "2018-03-04T19:24:48.474+00:00"}], [{"type": "kill", "data": {"actor": {"position": {"x": -1960, "y": 960, "z": 480}, "ingameTeam": "CT", "playerId": "flusha"}, "victim": {"position": {"x": -2727, "y": 272, "z": 496}, "ingameTeam": "TERRORIST", "playerId": "olofmeister"}, "weapon": "ump45", "headshot": false, "penetrated": false}, "roundIdx": 2, "date": "2018-03-04T19:27:11.630+00:00"}], [{"type": "kill", "data": {"actor": {"position": {"x": -2287, "y": -926, "z": 387}, "ingameTeam": "TERRORIST", "playerId": "rain"}, "victim": {"position": {"x": -2176, "y": -481, "z": 454}, "ingameTeam": "CT", "playerId": "JW"}, "weapon": "cz75a", "headshot": false, "penetrated": false}, "roundIdx": 2, "date": "2018-03-04T19:26:20.162+00:00"}], [{"type": "kill", "data": {"actor": {"position": {"x": -2658, "y": -1015, "z": 432}, "ingameTeam": "TERRORIST", "playerId": "olofmeister"}, "victim": {"position": {"x": -2357, "y": -1294, "z": 487}, "ingameTeam": "CT", "playerId": "Lekr0"}, "weapon": "deagle", "headshot": false, "penetrated": false}, "roundIdx": 2, "date": "2018-03-04T19:26:26.895+00:00"}], [{"type": "kill", "data": {"actor": {"position": {"x": -866, "y": -442, "z": 96}, "ingameTeam": "CT", "playerId": "Lekr0"}, "victim": {"position": {"x": -1963, "y": -1021, "z": 203}, "ingameTeam": "TERRORIST", "playerId": "rain"}, "weapon": "famas", "headshot": false, "penetrated": false}, "roundIdx": 3, "date": "2018-03-04T19:28:17.582+00:00"}], [{"type": "kill", "data": {"actor": {"position": {"x": -500, "y": -101, "z": 3}, "ingameTeam": "CT", "playerId": "Golden"}, "victim": {"position": {"x": -472, "y": -886, "z": 59}, "ingameTeam": "TERRORIST", "playerId": "karrigan"}, "weapon": "mp9", "headshot": false, "penetrated": false}, "roundIdx": 3, "date": "2018-03-04T19:28:17.019+00:00"}], [{"type": "kill", "data": {"actor": {"position": {"x": -2017, "y": -1298, "z": 292}, "ingameTeam": "CT", "playerId": "KRIMZ"}, "victim": {"position": {"x": -1908, "y": -906, "z": 192}, "ingameTeam": "TERRORIST", "playerId": "olofmeister"}, "weapon": "m4a1", "headshot": true, "penetrated": false}, "roundIdx": 3, "date": "2018-03-04T19:28:24.192+00:00"}], [{"type": "kill", "data": {"actor": {"position": {"x": -1808, "y": -322, "z": 128}, "ingameTeam": "CT", "playerId": "Lekr0"}, "victim": {"position": {"x": -378, "y": -15, "z": 80}, "ingameTeam": "TERRORIST", "playerId": "GuardiaN"}, "weapon": "awp", "headshot": false, "penetrated": false}, "roundIdx": 4, "date": "2018-03-04T19:30:28.551+00:00"}], [{"type": "kill", "data": {"actor": {"position": {"x": -873, "y": -414, "z": 96}, "ingameTeam": "CT", "playerId": "Golden"}, "victim": {"position": {"x": -1322, "y": -689, "z": 56}, "ingameTeam": "TERRORIST", "playerId": "NiKo"}, "weapon": "famas", "headshot": true, "penetrated": false}, "roundIdx": 4, "date": "2018-03-04T19:30:19.255+00:00"}], [{"type": "kill", "data": {"actor": {"position": {"x": -2226, "y": -57, "z": 399}, "ingameTeam": "CT", "playerId": "JW"}, "victim": {"position": {"x": -2249, "y": -840, "z": 449}, "ingameTeam": "TERRORIST", "playerId": "karrigan"}, "weapon": "m4a1", "headshot": false, "penetrated": false}, "roundIdx": 4, "date": "2018-03-04T19:30:16.754+00:00"}], [{"type": "kill", "data": {"actor": {"position": {"x": -3036, "y": -1619, "z": 552}, "ingameTeam": "TERRORIST", "playerId": "karrigan"}, "victim": {"position": {"x": -2300, "y": -1107, "z": 476}, "ingameTeam": "CT", "playerId": "KRIMZ"}, "weapon": "ak47", "headshot": false, "penetrated": false}, "roundIdx": 4, "date": "2018-03-04T19:29:13.490+00:00"}], [{"type": "kill", "data": {"actor": {"position": {"x": -3113, "y": -1850, "z": 512}, "ingameTeam": "TERRORIST", "playerId": "karrigan"}, "victim": {"position": {"x": -2901, "y": -1605, "z": 606}, "ingameTeam": "CT", "playerId": "KRIMZ"}, "weapon": "ak47", "headshot": false, "penetrated": false}, "roundIdx": 6, "date": "2018-03-04T19:33:03.217+00:00"}], [{"type": "kill", "data": {"actor": {"position": {"x": -1724, "y": -1111, "z": 96}, "ingameTeam": "TERRORIST", "playerId": "NiKo"}, "victim": {"position": {"x": -1932, "y": -990, "z": 192}, "ingameTeam": "CT", "playerId": "JW"}, "weapon": "ak47", "headshot": false, "penetrated": false}, "roundIdx": 6, "date": "2018-03-04T19:32:58.522+00:00"}], [{"type": "kill", "data": {"actor": {"position": {"x": -2004, "y": -1120, "z": 128}, "ingameTeam": "CT", "playerId": "JW"}, "victim": {"position": {"x": -1823, "y": -908, "z": 189}, "ingameTeam": "TERRORIST", "playerId": "rain"}, "weapon": "mag7", "headshot": false, "penetrated": false}, "roundIdx": 6, "date": "2018-03-04T19:32:56.366+00:00"}], [{"type": "kill", "data": {"actor": {"position": {"x": -2239, "y": 1019, "z": 480}, "ingameTeam": "CT", "playerId": "flusha"}, "victim": {"position": {"x": -2175, "y": 1022, "z": 544}, "ingameTeam": "TERRORIST", "playerId": "olofmeister"}, "weapon": "ak47", "headshot": false, "penetrated": false}, "roundIdx": 7, "date": "2018-03-04T19:35:25.482+00:00"}], [{"type": "kill", "data": {"actor": {"position": {"x": -2472, "y": 141, "z": 431}, "ingameTeam": "TERRORIST", "playerId": "NiKo"}, "victim": {"position": {"x": -2242, "y": 1018, "z": 544}, "ingameTeam": "CT", "playerId": "flusha"}, "weapon": "m4a1", "headshot": true, "penetrated": false}, "roundIdx": 7, "date": "2018-03-04T19:35:25.519+00:00"}], [{"type": "kill", "data": {"actor": {"position": {"x": -1097, "y": 363, "z": 67}, "ingameTeam": "CT", "playerId": "flusha"}, "victim": {"position": {"x": -734, "y": 19, "z": 119}, "ingameTeam": "TERRORIST", "playerId": "rain"}, "weapon": "m4a1", "headshot": false, "penetrated": false}, "roundIdx": 8, "date": "2018-03-04T19:37:04.983+00:00"}], [{"type": "kill", "data": {"actor": {"position": {"x": -2042, "y": -2560, "z": 448}, "ingameTeam": "TERRORIST", "playerId": "karrigan"}, "victim": {"position": {"x": -1841, "y": -2194, "z": 520}, "ingameTeam": "CT", "playerId": "KRIMZ"}, "weapon": "m4a1", "headshot": false, "penetrated": false}, "roundIdx": 8, "date": "2018-03-04T19:36:56.865+00:00"}], [{"type": "kill", "data": {"actor": {"position": {"x": -3763, "y": -478, "z": 500}, "ingameTeam": "CT", "playerId": "JW"}, "victim": {"position": {"x": -3099, "y": 241, "z": 529}, "ingameTeam": "TERRORIST", "playerId": "olofmeister"}, "weapon": "m4a1", "headshot": false, "penetrated": false}, "roundIdx": 8, "date": "2018-03-04T19:37:57.278+00:00"}], [{"type": "kill", "data": {"actor": {"position": {"x": -829, "y": 52, "z": 96}, "ingameTeam": "TERRORIST", "playerId": "olofmeister"}, "victim": {"position": {"x": -954, "y": -627, "z": 160}, "ingameTeam": "CT", "playerId": "Lekr0"}, "weapon": "ak47", "headshot": true, "penetrated": false}, "roundIdx": 8, "date": "2018-03-04T19:37:18.546+00:00"}], [{"type": "kill", "data": {"actor": {"position": {"x": -623, "y": -30, "z": 9}, "ingameTeam": "TERRORIST", "playerId": "rain"}, "victim": {"position": {"x": -888, "y": -112, "z": 160}, "ingameTeam": "CT", "playerId": "Golden"}, "weapon": "ak47", "headshot": false, "penetrated": false}, "roundIdx": 8, "date": "2018-03-04T19:37:03.849+00:00"}], [{"type": "kill", "data": {"actor": {"position": {"x": -738, "y": 115, "z": 57}, "ingameTeam": "CT", "playerId": "Golden"}, "victim": {"position": {"x": -515, "y": -201, "z": 53}, "ingameTeam": "TERRORIST", "playerId": "NiKo"}, "weapon": "m4a1", "headshot": true, "penetrated": false}, "roundIdx": 8, "date": "2018-03-04T19:36:58.334+00:00"}], [{"type": "kill", "data": {"actor": {"position": {"x": -1490, "y": -22, "z": 128}, "ingameTeam": "CT", "playerId": "Lekr0"}, "victim": {"position": {"x": -497, "y": 339, "z": 82}, "ingameTeam": "TERRORIST", "playerId": "NiKo"}, "weapon": "awp", "headshot": false, "penetrated": false}, "roundIdx": 9, "date": "2018-03-04T19:39:15.333+00:00"}], [{"type": "kill", "data": {"actor": {"position": {"x": -2738, "y": -896, "z": 432}, "ingameTeam": "CT", "playerId": "KRIMZ"}, "victim": {"position": {"x": -2634, "y": -1663, "z": 518}, "ingameTeam": "TERRORIST", "playerId": "karrigan"}, "weapon": "m4a1", "headshot": true, "penetrated": false}, "roundIdx": 9, "date": "2018-03-04T19:39:04.778+00:00"}], [{"type": "kill", "data": {"actor": {"position": {"x": -2471, "y": 823, "z": 472}, "ingameTeam": "CT", "playerId": "KRIMZ"}, "victim": {"position": {"x": -3086, "y": 629, "z": 543}, "ingameTeam": "TERRORIST", "playerId": "GuardiaN"}, "weapon": "awp", "headshot": false, "penetrated": false}, "roundIdx": 10, "date": "2018-03-04T19:43:53.326+00:00"}], [{"type": "kill", "data": {"actor": {"position": {"x": -2810, "y": -2185, "z": 472}, "ingameTeam": "TERRORIST", "playerId": "karrigan"}, "victim": {"position": {"x": -2643, "y": -1514, "z": 498}, "ingameTeam": "CT", "playerId": "KRIMZ"}, "weapon": "ak47", "headshot": true, "penetrated": false}, "roundIdx": 11, "date": "2018-03-04T19:45:37.566+00:00"}], [{"type": "kill", "data": {"actor": {"position": {"x": -1960, "y": -1026, "z": 142}, "ingameTeam": "CT", "playerId": "flusha"}, "victim": {"position": {"x": -1730, "y": -991, "z": 142}, "ingameTeam": "TERRORIST", "playerId": "karrigan"}, "weapon": "m4a1", "headshot": false, "penetrated": false}, "roundIdx": 12, "date": "2018-03-04T19:46:59.059+00:00"}], [{"type": "kill", "data": {"actor": {"position": {"x": -2460, "y": 1327, "z": 480}, "ingameTeam": "CT", "playerId": "Lekr0"}, "victim": {"position": {"x": -2392, "y": 244, "z": 557}, "ingameTeam": "TERRORIST", "playerId": "NiKo"}, "weapon": "awp", "headshot": false, "penetrated": false}, "roundIdx": 12, "date": "2018-03-04T19:48:10.217+00:00"}], [{"type": "kill", "data": {"actor": {"position": {"x": -1745, "y": 968, "z": 200}, "ingameTeam": "CT", "playerId": "Golden"}, "victim": {"position": {"x": -1782, "y": 1024, "z": 381}, "ingameTeam": "TERRORIST", "playerId": "rain"}, "weapon": "awp", "headshot": false, "penetrated": false}, "roundIdx": 12, "date": "2018-03-04T19:48:50.021+00:00"}], [{"type": "kill", "data": {"actor": {"position": {"x": -2853, "y": -884, "z": 432}, "ingameTeam": "CT", "playerId": "JW"}, "victim": {"position": {"x": -2359, "y": -1169, "z": 496}, "ingameTeam": "TERRORIST", "playerId": "GuardiaN"}, "weapon": "awp", "headshot": false, "penetrated": false}, "roundIdx": 12, "date": "2018-03-04T19:47:42.911+00:00"}], [{"type": "kill", "data": {"actor": {"position": {"x": -2184, "y": -716, "z": 384}, "ingameTeam": "TERRORIST", "playerId": "olofmeister"}, "victim": {"position": {"x": -2682, "y": 759, "z": 540}, "ingameTeam": "CT", "playerId": "Lekr0"}, "weapon": "awp", "headshot": false, "penetrated": false}, "roundIdx": 12, "date": "2018-03-04T19:48:32.959+00:00"}], [{"type": "kill", "data": {"actor": {"position": {"x": -2142, "y": -1075, "z": 394}, "ingameTeam": "CT", "playerId": "Golden"}, "victim": {"position": {"x": -2402, "y": 151, "z": 499}, "ingameTeam": "TERRORIST", "playerId": "NiKo"}, "weapon": "awp", "headshot": false, "penetrated": false}, "roundIdx": 13, "date": "2018-03-04T19:51:15.887+00:00"}], [{"type": "kill", "data": {"actor": {"position": {"x": -2696, "y": 289, "z": 436}, "ingameTeam": "TERRORIST", "playerId": "rain"}, "victim": {"position": {"x": -2079, "y": 775, "z": 539}, "ingameTeam": "CT", "playerId": "Lekr0"}, "weapon": "ak47", "headshot": false, "penetrated": false}, "roundIdx": 13, "date": "2018-03-04T19:51:11.262+00:00"}], [{"type": "kill", "data": {"actor": {"position": {"x": -2032, "y": -1313, "z": 302}, "ingameTeam": "TERRORIST", "playerId": "olofmeister"}, "victim": {"position": {"x": -1939, "y": -1009, "z": 194}, "ingameTeam": "CT", "playerId": "JW"}, "weapon": "ak47", "headshot": true, "penetrated": false}, "roundIdx": 13, "date": "2018-03-04T19:50:49.238+00:00"}], [{"type": "kill", "data": {"actor": {"position": {"x": -2679, "y": 237, "z": 432}, "ingameTeam": "TERRORIST", "playerId": "karrigan"}, "victim": {"position": {"x": -1970, "y": 883, "z": 544}, "ingameTeam": "CT", "playerId": "flusha"}, "weapon": "ak47", "headshot": false, "penetrated": false}, "roundIdx": 13, "date": "2018-03-04T19:51:07.521+00:00"}], [{"type": "kill", "data": {"actor": {"position": {"x": -1830, "y": -1060, "z": 96}, "ingameTeam": "TERRORIST", "playerId": "rain"}, "victim": {"position": {"x": -2096, "y": -1320, "z": 408}, "ingameTeam": "CT", "playerId": "KRIMZ"}, "weapon": "ak47", "headshot": false, "penetrated": false}, "roundIdx": 14, "date": "2018-03-04T19:52:59.014+00:00"}], [{"type": "kill", "data": {"actor": {"position": {"x": -1842, "y": -949, "z": 128}, "ingameTeam": "TERRORIST", "playerId": "NiKo"}, "victim": {"position": {"x": -1955, "y": -1311, "z": 314}, "ingameTeam": "CT", "playerId": "flusha"}, "weapon": "ak47", "headshot": false, "penetrated": false}, "roundIdx": 14, "date": "2018-03-04T19:53:02.230+00:00"}], [{"type": "kill", "data": {"actor": {"position": {"x": -1541, "y": -396, "z": 27}, "ingameTeam": "TERRORIST", "playerId": "karrigan"}, "victim": {"position": {"x": -1720, "y": -888, "z": 160}, "ingameTeam": "CT", "playerId": "flusha"}, "weapon": "ak47", "headshot": false, "penetrated": false}, "roundIdx": 15, "date": "2018-03-04T19:54:21.343+00:00"}], [{"type": "kill", "data": {"actor": {"position": {"x": -1097, "y": 19, "z": 98}, "ingameTeam": "CT", "playerId": "Golden"}, "victim": {"position": {"x": -552, "y": -172, "z": 67}, "ingameTeam": "TERRORIST", "playerId": "olofmeister"}, "weapon": "m4a1", "headshot": false, "penetrated": false}, "roundIdx": 15, "date": "2018-03-04T19:54:21.426+00:00"}], [{"type": "kill", "data": {"actor": {"position": {"x": -1796, "y": 544, "z": 256}, "ingameTeam": "CT", "playerId": "olofmeister"}, "victim": {"position": {"x": -820, "y": 105, "z": 160}, "ingameTeam": "TERRORIST", "playerId": "Golden"}, "weapon": "usp_silencer", "headshot": true, "penetrated": false}, "roundIdx": 16, "date": "2018-03-04T20:01:36.786+00:00"}], [{"type": "kill", "data": {"actor": {"position": {"x": -1961, "y": -31, "z": 128}, "ingameTeam": "CT", "playerId": "GuardiaN"}, "victim": {"position": {"x": -916, "y": -312, "z": 160}, "ingameTeam": "TERRORIST", "playerId": "Lekr0"}, "weapon": "hkp2000", "headshot": true, "penetrated": false}, "roundIdx": 16, "date": "2018-03-04T20:01:13.519+00:00"}], [{"type": "kill", "data": {"actor": {"position": {"x": -1020, "y": 135, "z": 99}, "ingameTeam": "TERRORIST", "playerId": "KRIMZ"}, "victim": {"position": {"x": -1875, "y": 540, "z": 320}, "ingameTeam": "CT", "playerId": "karrigan"}, "weapon": "glock", "headshot": true, "penetrated": false}, "roundIdx": 16, "date": "2018-03-04T20:01:16.122+00:00"}], [{"type": "kill", "data": {"actor": {"position": {"x": -771, "y": 297, "z": 74}, "ingameTeam": "TERRORIST", "playerId": "Lekr0"}, "victim": {"position": {"x": -1884, "y": -362, "z": 192}, "ingameTeam": "CT", "playerId": "olofmeister"}, "weapon": "galilar", "headshot": false, "penetrated": false}, "roundIdx": 17, "date": "2018-03-04T20:03:39.722+00:00"}], [{"type": "kill", "data": {"actor": {"position": {"x": -2452, "y": -1153, "z": 434}, "ingameTeam": "TERRORIST", "playerId": "JW"}, "victim": {"position": {"x": -2775, "y": -913, "z": 478}, "ingameTeam": "CT", "playerId": "rain"}, "weapon": "ak47", "headshot": false, "penetrated": false}, "roundIdx": 17, "date": "2018-03-04T20:03:17.746+00:00"}], [{"type": "kill", "data": {"actor": {"position": {"x": -880, "y": -308, "z": 96}, "ingameTeam": "CT", "playerId": "olofmeister"}, "victim": {"position": {"x": -1146, "y": -630, "z": 120}, "ingameTeam": "TERRORIST", "playerId": "Golden"}, "weapon": "cz75a", "headshot": true, "penetrated": false}, "roundIdx": 17, "date": "2018-03-04T20:02:34.529+00:00"}], [{"type": "kill", "data": {"actor": {"position": {"x": -2776, "y": -904, "z": 432}, "ingameTeam": "CT", "playerId": "rain"}, "victim": {"position": {"x": -2320, "y": -1353, "z": 496}, "ingameTeam": "TERRORIST", "playerId": "flusha"}, "weapon": "cz75a", "headshot": true, "penetrated": false}, "roundIdx": 17, "date": "2018-03-04T20:03:15.679+00:00"}], [{"type": "kill", "data": {"actor": {"position": {"x": -1849, "y": -34, "z": 128}, "ingameTeam": "CT", "playerId": "GuardiaN"}, "victim": {"position": {"x": -986, "y": -281, "z": 142}, "ingameTeam": "TERRORIST", "playerId": "JW"}, "weapon": "cz75a", "headshot": false, "penetrated": false}, "roundIdx": 17, "date": "2018-03-04T20:03:40.357+00:00"}], [{"type": "kill", "data": {"actor": {"position": {"x": -2702, "y": -1692, "z": 471}, "ingameTeam": "CT", "playerId": "karrigan"}, "victim": {"position": {"x": -2518, "y": -1839, "z": 536}, "ingameTeam": "TERRORIST", "playerId": "flusha"}, "weapon": "usp_silencer", "headshot": false, "penetrated": false}, "roundIdx": 18, "date": "2018-03-04T20:04:19.521+00:00"}], [{"type": "kill", "data": {"actor": {"position": {"x": -1820, "y": -1502, "z": 96}, "ingameTeam": "TERRORIST", "playerId": "KRIMZ"}, "victim": {"position": {"x": -1749, "y": -1861, "z": 160}, "ingameTeam": "CT", "playerId": "karrigan"}, "weapon": "ak47", "headshot": false, "penetrated": false}, "roundIdx": 18, "date": "2018-03-04T20:04:40.089+00:00"}], [{"type": "kill", "data": {"actor": {"position": {"x": -542, "y": -282, "z": 6}, "ingameTeam": "CT", "playerId": "olofmeister"}, "victim": {"position": {"x": -555, "y": -437, "z": 53}, "ingameTeam": "TERRORIST", "playerId": "KRIMZ"}, "weapon": "m4a1", "headshot": true, "penetrated": false}, "roundIdx": 19, "date": "2018-03-04T20:07:04.090+00:00"}], [{"type": "kill", "data": {"actor": {"position": {"x": -1539, "y": -257, "z": 128}, "ingameTeam": "CT", "playerId": "karrigan"}, "victim": {"position": {"x": -1244, "y": 474, "z": 89}, "ingameTeam": "TERRORIST", "playerId": "Golden"}, "weapon": "m4a1_silencer", "headshot": false, "penetrated": false}, "roundIdx": 19, "date": "2018-03-04T20:07:09.294+00:00"}], [{"type": "kill", "data": {"actor": {"position": {"x": -2323, "y": 439, "z": 480}, "ingameTeam": "TERRORIST", "playerId": "JW"}, "victim": {"position": {"x": -3105, "y": 732, "z": 544}, "ingameTeam": "CT", "playerId": "rain"}, "weapon": "ak47", "headshot": true, "penetrated": false}, "roundIdx": 19, "date": "2018-03-04T20:07:02.645+00:00"}], [{"type": "kill", "data": {"actor": {"position": {"x": -2357, "y": -2731, "z": 487}, "ingameTeam": "TERRORIST", "playerId": "Lekr0"}, "victim": {"position": {"x": -3771, "y": -1923, "z": 553}, "ingameTeam": "CT", "playerId": "karrigan"}, "weapon": "m4a1_silencer", "headshot": false, "penetrated": false}, "roundIdx": 20, "date": "2018-03-04T20:07:55.425+00:00"}], [{"type": "kill", "data": {"actor": {"position": {"x": -2551, "y": -1145, "z": 434}, "ingameTeam": "CT", "playerId": "NiKo"}, "victim": {"position": {"x": -2652, "y": -995, "z": 495}, "ingameTeam": "TERRORIST", "playerId": "KRIMZ"}, "weapon": "deagle", "headshot": false, "penetrated": false}, "roundIdx": 20, "date": "2018-03-04T20:08:54.981+00:00"}], [{"type": "kill", "data": {"actor": {"position": {"x": -3621, "y": -1228, "z": 482}, "ingameTeam": "TERRORIST", "playerId": "JW"}, "victim": {"position": {"x": -3691, "y": -348, "z": 578}, "ingameTeam": "CT", "playerId": "GuardiaN"}, "weapon": "ak47", "headshot": false, "penetrated": false}, "roundIdx": 20, "date": "2018-03-04T20:08:53.590+00:00"}], [{"type": "kill", "data": {"actor": {"position": {"x": -1449, "y": -861, "z": 35}, "ingameTeam": "TERRORIST", "playerId": "Lekr0"}, "victim": {"position": {"x": -864, "y": -346, "z": 145}, "ingameTeam": "CT", "playerId": "olofmeister"}, "weapon": "ak47", "headshot": true, "penetrated": false}, "roundIdx": 21, "date": "2018-03-04T20:09:59.520+00:00"}], [{"type": "kill", "data": {"actor": {"position": {"x": -726, "y": 52, "z": 51}, "ingameTeam": "CT", "playerId": "NiKo"}, "victim": {"position": {"x": -1115, "y": -634, "z": 153}, "ingameTeam": "TERRORIST", "playerId": "Lekr0"}, "weapon": "m4a1", "headshot": false, "penetrated": true}, "roundIdx": 21, "date": "2018-03-04T20:10:10.255+00:00"}], [{"type": "kill", "data": {"actor": {"position": {"x": -2485, "y": 570, "z": 480}, "ingameTeam": "TERRORIST", "playerId": "JW"}, "victim": {"position": {"x": -1869, "y": 981, "z": 544}, "ingameTeam": "CT", "playerId": "karrigan"}, "weapon": "ak47", "headshot": true, "penetrated": false}, "roundIdx": 21, "date": "2018-03-04T20:11:21.746+00:00"}], [{"type": "kill", "data": {"actor": {"position": {"x": -1772, "y": -1478, "z": 96}, "ingameTeam": "TERRORIST", "playerId": "KRIMZ"}, "victim": {"position": {"x": -1876, "y": -1615, "z": 151}, "ingameTeam": "CT", "playerId": "NiKo"}, "weapon": "ak47", "headshot": true, "penetrated": false}, "roundIdx": 21, "date": "2018-03-04T20:12:04.091+00:00"}], [{"type": "kill", "data": {"actor": {"position": {"x": -628, "y": -29, "z": 11}, "ingameTeam": "CT", "playerId": "NiKo"}, "victim": {"position": {"x": -386, "y": -1160, "z": 68}, "ingameTeam": "TERRORIST", "playerId": "flusha"}, "weapon": "m4a1", "headshot": false, "penetrated": false}, "roundIdx": 22, "date": "2018-03-04T20:12:42.638+00:00"}], [{"type": "kill", "data": {"actor": {"position": {"x": -3485, "y": -152, "z": 514}, "ingameTeam": "CT", "playerId": "GuardiaN"}, "victim": {"position": {"x": -3038, "y": 761, "z": 543}, "ingameTeam": "TERRORIST", "playerId": "Lekr0"}, "weapon": "famas", "headshot": false, "penetrated": false}, "roundIdx": 22, "date": "2018-03-04T20:14:05.090+00:00"}], [{"type": "kill", "data": {"actor": {"position": {"x": -3680, "y": -649, "z": 489}, "ingameTeam": "TERRORIST", "playerId": "JW"}, "victim": {"position": {"x": -3614, "y": -130, "z": 575}, "ingameTeam": "CT", "playerId": "GuardiaN"}, "weapon": "ak47", "headshot": false, "penetrated": true}, "roundIdx": 22, "date": "2018-03-04T20:14:10.317+00:00"}], [{"type": "kill", "data": {"actor": {"position": {"x": -402, "y": -1307, "z": 52}, "ingameTeam": "TERRORIST", "playerId": "flusha"}, "victim": {"position": {"x": -631, "y": 13, "z": 75}, "ingameTeam": "CT", "playerId": "NiKo"}, "weapon": "ak47", "headshot": false, "penetrated": false}, "roundIdx": 23, "date": "2018-03-04T20:15:25.411+00:00"}], [{"type": "kill", "data": {"actor": {"position": {"x": -1047, "y": -266, "z": 98}, "ingameTeam": "CT", "playerId": "karrigan"}, "victim": {"position": {"x": -353, "y": 244, "z": 75}, "ingameTeam": "TERRORIST", "playerId": "Lekr0"}, "weapon": "famas", "headshot": true, "penetrated": false}, "roundIdx": 23, "date": "2018-03-04T20:16:32.707+00:00"}], [{"type": "kill", "data": {"actor": {"position": {"x": -1976, "y": -1132, "z": 128}, "ingameTeam": "CT", "playerId": "olofmeister"}, "victim": {"position": {"x": -2048, "y": -1326, "z": 376}, "ingameTeam": "TERRORIST", "playerId": "JW"}, "weapon": "mag7", "headshot": true, "penetrated": false}, "roundIdx": 23, "date": "2018-03-04T20:16:09.622+00:00"}], [{"type": "kill", "data": {"actor": {"position": {"x": -955, "y": 361, "z": 96}, "ingameTeam": "CT", "playerId": "rain"}, "victim": {"position": {"x": -338, "y": -110, "z": 73}, "ingameTeam": "TERRORIST", "playerId": "flusha"}, "weapon": "m4a1", "headshot": false, "penetrated": false}, "roundIdx": 23, "date": "2018-03-04T20:16:34.207+00:00"}], [{"type": "kill", "data": {"actor": {"position": {"x": -1516, "y": 82, "z": 101}, "ingameTeam": "CT", "playerId": "GuardiaN"}, "victim": {"position": {"x": -731, "y": -59, "z": 117}, "ingameTeam": "TERRORIST", "playerId": "Golden"}, "weapon": "m4a1", "headshot": false, "penetrated": false}, "roundIdx": 23, "date": "2018-03-04T20:16:43.490+00:00"}]], "2": [[{"type": "kill", "data": {"actor": {"position": {"x": -1587, "y": 137, "z": 86}, "ingameTeam": "CT", "playerId": "Golden"}, "victim": {"position": {"x": -1022, "y": 349, "z": 160}, "ingameTeam": "TERRORIST", "playerId": "karrigan"}, "weapon": "usp_silencer", "headshot": true, "penetrated": false}, "roundIdx": 1, "date": "2018-03-04T19:24:42.178+00:00"}, {"type": "kill", "data": {"actor": {"position": {"x": -1579, "y": 159, "z": 76}, "ingameTeam": "CT", "playerId": "Golden"}, "victim": {"position": {"x": -868, "y": -75, "z": 160}, "ingameTeam": "TERRORIST", "playerId": "GuardiaN"}, "weapon": "usp_silencer", "headshot": true, "penetrated": false}, "roundIdx": 1, "date": "2018-03-04T19:24:42.997+00:00"}], [{"type": "kill", "data": {"actor": {"position": {"x": -1967, "y": 702, "z": 256}, "ingameTeam": "CT", "playerId": "KRIMZ"}, "victim": {"position": {"x": -869, "y": -164, "z": 160}, "ingameTeam": "TERRORIST", "playerId": "olofmeister"}, "weapon": "usp_silencer", "headshot": false, "penetrated": false}, "roundIdx": 1, "date": "2018-03-04T19:24:49.186+00:00"}, {"type": "kill", "data": {"actor": {"position": {"x": -1878, "y": 510, "z": 256}, "ingameTeam": "CT", "playerId": "KRIMZ"}, "victim": {"position": {"x": -605, "y": 44, "z": 52}, "ingameTeam": "TERRORIST", "playerId": "rain"}, "weapon": "usp_silencer", "headshot": true, "penetrated": false}, "roundIdx": 1, "date": "2018-03-04T19:24:57.607+00:00"}], [{"type": "kill", "data": {"actor": {"position": {"x": -1320, "y": -632, "z": 23}, "ingameTeam": "CT", "playerId": "Lekr0"}, "victim": {"position": {"x": -1278, "y": -868, "z": 57}, "ingameTeam": "TERRORIST", "playerId": "NiKo"}, "weapon": "mp9", "headshot": true, "penetrated": false}, "roundIdx": 2, "date": "2018-03-04T19:25:36.457+00:00"}, {"type": "kill", "data": {"actor": {"position": {"x": -2370, "y": -1293, "z": 433}, "ingameTeam": "CT", "playerId": "Lekr0"}, "victim": {"position": {"x": -2255, "y": -972, "z": 453}, "ingameTeam": "TERRORIST", "playerId": "rain"}, "weapon": "mp9", "headshot": true, "penetrated": false}, "roundIdx": 2, "date": "2018-03-04T19:26:26.654+00:00"}], [{"type": "kill", "data": {"actor": {"position": {"x": -2713, "y": 705, "z": 480}, "ingameTeam": "CT", "playerId": "KRIMZ"}, "victim": {"position": {"x": -2012, "y": -904, "z": 458}, "ingameTeam": "TERRORIST", "playerId": "karrigan"}, "weapon": "m4a1", "headshot": false, "penetrated": false}, "roundIdx": 2, "date": "2018-03-04T19:26:18.646+00:00"}, {"type": "kill", "data": {"actor": {"position": {"x": -2367, "y": 1218, "z": 480}, "ingameTeam": "CT", "playerId": "KRIMZ"}, "victim": {"position": {"x": -2399, "y": 249, "z": 556}, "ingameTeam": "TERRORIST", "playerId": "GuardiaN"}, "weapon": "m4a1", "headshot": false, "penetrated": false}, "roundIdx": 2, "date": "2018-03-04T19:27:09.171+00:00"}], [{"type": "kill", "data": {"actor": {"position": {"x": -1584, "y": -1082, "z": 178}, "ingameTeam": "CT", "playerId": "flusha"}, "victim": {"position": {"x": -2148, "y": -924, "z": 192}, "ingameTeam": "TERRORIST", "playerId": "NiKo"}, "weapon": "ump45", "headshot": false, "penetrated": false}, "roundIdx": 3, "date": "2018-03-04T19:28:24.029+00:00"}, {"type": "kill", "data": {"actor": {"position": {"x": -1699, "y": -805, "z": 96}, "ingameTeam": "CT", "playerId": "flusha"}, "victim": {"position": {"x": -1715, "y": -864, "z": 160}, "ingameTeam": "TERRORIST", "playerId": "GuardiaN"}, "weapon": "ump45", "headshot": false, "penetrated": false}, "roundIdx": 3, "date": "2018-03-04T19:28:26.787+00:00"}], [{"type": "kill", "data": {"actor": {"position": {"x": -2173, "y": -316, "z": 393}, "ingameTeam": "CT", "playerId": "flusha"}, "victim": {"position": {"x": -2352, "y": -790, "z": 453}, "ingameTeam": "TERRORIST", "playerId": "rain"}, "weapon": "ump45", "headshot": false, "penetrated": false}, "roundIdx": 4, "date": "2018-03-04T19:29:56.474+00:00"}, {"type": "kill", "data": {"actor": {"position": {"x": -958, "y": 470, "z": 96}, "ingameTeam": "CT", "playerId": "flusha"}, "victim": {"position": {"x": -581, "y": -171, "z": 69}, "ingameTeam": "TERRORIST", "playerId": "olofmeister"}, "weapon": "ump45", "headshot": true, "penetrated": false}, "roundIdx": 4, "date": "2018-03-04T19:30:38.559+00:00"}], [{"type": "kill", "data": {"actor": {"position": {"x": -2335, "y": -1320, "z": 432}, "ingameTeam": "TERRORIST", "playerId": "olofmeister"}, "victim": {"position": {"x": -2189, "y": -62, "z": 456}, "ingameTeam": "CT", "playerId": "JW"}, "weapon": "ak47", "headshot": true, "penetrated": false}, "roundIdx": 4, "date": "2018-03-04T19:30:17.786+00:00"}, {"type": "kill", "data": {"actor": {"position": {"x": -1711, "y": -836, "z": 96}, "ingameTeam": "TERRORIST", "playerId": "olofmeister"}, "victim": {"position": {"x": -1088, "y": -614, "z": 160}, "ingameTeam": "CT", "playerId": "Golden"}, "weapon": "ak47", "headshot": false, "penetrated": false}, "roundIdx": 4, "date": "2018-03-04T19:30:22.889+00:00"}], [{"type": "kill", "data": {"actor": {"position": {"x": -1883, "y": -36, "z": 128}, "ingameTeam": "CT", "playerId": "flusha"}, "victim": {"position": {"x": -1618, "y": -28, "z": 192}, "ingameTeam": "TERRORIST", "playerId": "karrigan"}, "weapon": "ak47", "headshot": false, "penetrated": false}, "roundIdx": 5, "date": "2018-03-04T19:31:44.231+00:00"}, {"type": "kill", "data": {"actor": {"position": {"x": -1869, "y": -109, "z": 128}, "ingameTeam": "CT", "playerId": "flusha"}, "victim": {"position": {"x": -1456, "y": 46, "z": 148}, "ingameTeam": "TERRORIST", "playerId": "olofmeister"}, "weapon": "ak47", "headshot": false, "penetrated": false}, "roundIdx": 5, "date": "2018-03-04T19:31:45.606+00:00"}], [{"type": "kill", "data": {"actor": {"position": {"x": -2333, "y": -917, "z": 387}, "ingameTeam": "CT", "playerId": "flusha"}, "victim": {"position": {"x": -2345, "y": -885, "z": 452}, "ingameTeam": "TERRORIST", "playerId": "NiKo"}, "weapon": "knife_default_ct", "headshot": false, "penetrated": false}, "roundIdx": 6, "date": "2018-03-04T19:33:46.926+00:00"}, {"type": "kill", "data": {"actor": {"position": {"x": -2345, "y": -1012, "z": 399}, "ingameTeam": "CT", "playerId": "flusha"}, "victim": {"position": {"x": -2334, "y": -769, "z": 495}, "ingameTeam": "TERRORIST", "playerId": "karrigan"}, "weapon": "ak47", "headshot": true, "penetrated": false}, "roundIdx": 6, "date": "2018-03-04T19:33:48.255+00:00"}], [{"type": "kill", "data": {"actor": {"position": {"x": -2979, "y": -1647, "z": 521}, "ingameTeam": "CT", "playerId": "KRIMZ"}, "victim": {"position": {"x": -3109, "y": -2452, "z": 546}, "ingameTeam": "TERRORIST", "playerId": "GuardiaN"}, "weapon": "m4a1", "headshot": false, "penetrated": false}, "roundIdx": 6, "date": "2018-03-04T19:32:59.162+00:00"}, {"type": "kill", "data": {"actor": {"position": {"x": -2914, "y": -1599, "z": 549}, "ingameTeam": "CT", "playerId": "KRIMZ"}, "victim": {"position": {"x": -2574, "y": -1707, "z": 535}, "ingameTeam": "TERRORIST", "playerId": "olofmeister"}, "weapon": "m4a1", "headshot": false, "penetrated": false}, "roundIdx": 6, "date": "2018-03-04T19:33:00.429+00:00"}], [{"type": "kill", "data": {"actor": {"position": {"x": -2306, "y": -527, "z": 399}, "ingameTeam": "TERRORIST", "playerId": "karrigan"}, "victim": {"position": {"x": -2544, "y": -645, "z": 496}, "ingameTeam": "CT", "playerId": "KRIMZ"}, "weapon": "cz75a", "headshot": false, "penetrated": false}, "roundIdx": 7, "date": "2018-03-04T19:35:10.490+00:00"}, {"type": "kill", "data": {"actor": {"position": {"x": -2372, "y": -1171, "z": 432}, "ingameTeam": "TERRORIST", "playerId": "karrigan"}, "victim": {"position": {"x": -2303, "y": -1301, "z": 496}, "ingameTeam": "CT", "playerId": "JW"}, "weapon": "cz75a", "headshot": true, "penetrated": false}, "roundIdx": 7, "date": "2018-03-04T19:35:31.911+00:00"}], [{"type": "kill", "data": {"actor": {"position": {"x": -687, "y": 302, "z": 31}, "ingameTeam": "TERRORIST", "playerId": "GuardiaN"}, "victim": {"position": {"x": -1059, "y": 249, "z": 163}, "ingameTeam": "CT", "playerId": "flusha"}, "weapon": "awp", "headshot": false, "penetrated": false}, "roundIdx": 8, "date": "2018-03-04T19:37:07.365+00:00"}, {"type": "kill", "data": {"actor": {"position": {"x": -2222, "y": 750, "z": 472}, "ingameTeam": "TERRORIST", "playerId": "GuardiaN"}, "victim": {"position": {"x": -2228, "y": 473, "z": 544}, "ingameTeam": "CT", "playerId": "JW"}, "weapon": "awp", "headshot": false, "penetrated": false}, "roundIdx": 8, "date": "2018-03-04T19:38:16.614+00:00"}], [{"type": "kill", "data": {"actor": {"position": {"x": -1068, "y": 19, "z": 98}, "ingameTeam": "CT", "playerId": "Golden"}, "victim": {"position": {"x": -563, "y": -169, "z": 68}, "ingameTeam": "TERRORIST", "playerId": "rain"}, "weapon": "m4a1", "headshot": false, "penetrated": true}, "roundIdx": 9, "date": "2018-03-04T19:39:16.410+00:00"}, {"type": "kill", "data": {"actor": {"position": {"x": -940, "y": 227, "z": 96}, "ingameTeam": "CT", "playerId": "Golden"}, "victim": {"position": {"x": -572, "y": -143, "z": 50}, "ingameTeam": "TERRORIST", "playerId": "olofmeister"}, "weapon": "m4a1", "headshot": false, "penetrated": false}, "roundIdx": 9, "date": "2018-03-04T19:39:18.786+00:00"}], [{"type": "kill", "data": {"actor": {"position": {"x": -2407, "y": 138, "z": 431}, "ingameTeam": "TERRORIST", "playerId": "karrigan"}, "victim": {"position": {"x": -2435, "y": 1323, "z": 544}, "ingameTeam": "CT", "playerId": "flusha"}, "weapon": "ak47", "headshot": true, "penetrated": false}, "roundIdx": 10, "date": "2018-03-04T19:43:50.066+00:00"}, {"type": "kill", "data": {"actor": {"position": {"x": -2296, "y": 436, "z": 480}, "ingameTeam": "TERRORIST", "playerId": "karrigan"}, "victim": {"position": {"x": -2404, "y": 785, "z": 536}, "ingameTeam": "CT", "playerId": "KRIMZ"}, "weapon": "ak47", "headshot": false, "penetrated": false}, "roundIdx": 10, "date": "2018-03-04T19:43:54.042+00:00"}], [{"type": "kill", "data": {"actor": {"position": {"x": -1280, "y": -766, "z": 11}, "ingameTeam": "TERRORIST", "playerId": "NiKo"}, "victim": {"position": {"x": -1198, "y": -522, "z": 115}, "ingameTeam": "CT", "playerId": "Golden"}, "weapon": "ak47", "headshot": true, "penetrated": false}, "roundIdx": 11, "date": "2018-03-04T19:45:48.879+00:00"}, {"type": "kill", "data": {"actor": {"position": {"x": -558, "y": -62, "z": 2}, "ingameTeam": "TERRORIST", "playerId": "NiKo"}, "victim": {"position": {"x": -1284, "y": -146, "z": 205}, "ingameTeam": "CT", "playerId": "Lekr0"}, "weapon": "ak47", "headshot": true, "penetrated": true}, "roundIdx": 11, "date": "2018-03-04T19:46:10.863+00:00"}], [{"type": "kill", "data": {"actor": {"position": {"x": -2014, "y": -1323, "z": 289}, "ingameTeam": "TERRORIST", "playerId": "olofmeister"}, "victim": {"position": {"x": -2028, "y": -811, "z": 192}, "ingameTeam": "CT", "playerId": "JW"}, "weapon": "ak47", "headshot": false, "penetrated": false}, "roundIdx": 11, "date": "2018-03-04T19:45:48.193+00:00"}, {"type": "kill", "data": {"actor": {"position": {"x": -2206, "y": -1328, "z": 417}, "ingameTeam": "TERRORIST", "playerId": "olofmeister"}, "victim": {"position": {"x": -2803, "y": -920, "z": 496}, "ingameTeam": "CT", "playerId": "flusha"}, "weapon": "ak47", "headshot": true, "penetrated": false}, "roundIdx": 11, "date": "2018-03-04T19:45:57.871+00:00"}], [{"type": "kill", "data": {"actor": {"position": {"x": -2561, "y": 799, "z": 475}, "ingameTeam": "CT", "playerId": "KRIMZ"}, "victim": {"position": {"x": -2828, "y": 646, "z": 544}, "ingameTeam": "TERRORIST", "playerId": "olofmeister"}, "weapon": "cz75a", "headshot": false, "penetrated": false}, "roundIdx": 13, "date": "2018-03-04T19:51:04.130+00:00"}, {"type": "kill", "data": {"actor": {"position": {"x": -2636, "y": 831, "z": 475}, "ingameTeam": "CT", "playerId": "KRIMZ"}, "victim": {"position": {"x": -2735, "y": 259, "z": 496}, "ingameTeam": "TERRORIST", "playerId": "karrigan"}, "weapon": "cz75a", "headshot": true, "penetrated": false}, "roundIdx": 13, "date": "2018-03-04T19:51:08.411+00:00"}], [{"type": "kill", "data": {"actor": {"position": {"x": -2254, "y": 627, "z": 475}, "ingameTeam": "TERRORIST", "playerId": "GuardiaN"}, "victim": {"position": {"x": -2988, "y": 614, "z": 591}, "ingameTeam": "CT", "playerId": "KRIMZ"}, "weapon": "ak47", "headshot": false, "penetrated": false}, "roundIdx": 13, "date": "2018-03-04T19:51:19.045+00:00"}, {"type": "kill", "data": {"actor": {"position": {"x": -1940, "y": 1175, "z": 353}, "ingameTeam": "TERRORIST", "playerId": "GuardiaN"}, "victim": {"position": {"x": -1878, "y": 1000, "z": 530}, "ingameTeam": "CT", "playerId": "Golden"}, "weapon": "ak47", "headshot": true, "penetrated": false}, "roundIdx": 13, "date": "2018-03-04T19:51:44.019+00:00"}], [{"type": "kill", "data": {"actor": {"position": {"x": -1933, "y": -1131, "z": 212}, "ingameTeam": "CT", "playerId": "flusha"}, "victim": {"position": {"x": -1788, "y": -920, "z": 165}, "ingameTeam": "TERRORIST", "playerId": "olofmeister"}, "weapon": "m4a1", "headshot": false, "penetrated": false}, "roundIdx": 14, "date": "2018-03-04T19:52:57.170+00:00"}, {"type": "kill", "data": {"actor": {"position": {"x": -1911, "y": -1325, "z": 240}, "ingameTeam": "CT", "playerId": "flusha"}, "victim": {"position": {"x": -1852, "y": -948, "z": 174}, "ingameTeam": "TERRORIST", "playerId": "rain"}, "weapon": "m4a1", "headshot": false, "penetrated": false}, "roundIdx": 14, "date": "2018-03-04T19:53:01.389+00:00"}], [{"type": "kill", "data": {"actor": {"position": {"x": -846, "y": 393, "z": 96}, "ingameTeam": "CT", "playerId": "Lekr0"}, "victim": {"position": {"x": -526, "y": -328, "z": 73}, "ingameTeam": "TERRORIST", "playerId": "karrigan"}, "weapon": "m4a1", "headshot": true, "penetrated": false}, "roundIdx": 14, "date": "2018-03-04T19:52:34.793+00:00"}, {"type": "kill", "data": {"actor": {"position": {"x": -874, "y": -435, "z": 96}, "ingameTeam": "CT", "playerId": "Lekr0"}, "victim": {"position": {"x": -1818, "y": -942, "z": 167}, "ingameTeam": "TERRORIST", "playerId": "NiKo"}, "weapon": "m4a1", "headshot": true, "penetrated": false}, "roundIdx": 14, "date": "2018-03-04T19:53:03.989+00:00"}], [{"type": "kill", "data": {"actor": {"position": {"x": -1017, "y": 490, "z": 96}, "ingameTeam": "CT", "playerId": "Golden"}, "victim": {"position": {"x": -1030, "y": -260, "z": 154}, "ingameTeam": "CT", "playerId": "Lekr0"}, "weapon": "m4a1", "headshot": true, "penetrated": false}, "roundIdx": 14, "date": "2018-03-04T19:53:32.334+00:00"}, {"type": "kill", "data": {"actor": {"position": {"x": -1016, "y": 490, "z": 96}, "ingameTeam": "CT", "playerId": "Golden"}, "victim": {"position": {"x": -982, "y": -421, "z": 160}, "ingameTeam": "TERRORIST", "playerId": "GuardiaN"}, "weapon": "m4a1", "headshot": false, "penetrated": false}, "roundIdx": 14, "date": "2018-03-04T19:53:33.301+00:00"}], [{"type": "kill", "data": {"actor": {"position": {"x": -883, "y": -360, "z": 96}, "ingameTeam": "CT", "playerId": "Lekr0"}, "victim": {"position": {"x": -1114, "y": -640, "z": 151}, "ingameTeam": "TERRORIST", "playerId": "NiKo"}, "weapon": "awp", "headshot": false, "penetrated": false}, "roundIdx": 15, "date": "2018-03-04T19:54:18.802+00:00"}, {"type": "kill", "data": {"actor": {"position": {"x": -1223, "y": -252, "z": 100}, "ingameTeam": "CT", "playerId": "Lekr0"}, "victim": {"position": {"x": -347, "y": 76, "z": 76}, "ingameTeam": "TERRORIST", "playerId": "rain"}, "weapon": "awp", "headshot": false, "penetrated": false}, "roundIdx": 15, "date": "2018-03-04T19:54:21.082+00:00"}], [{"type": "kill", "data": {"actor": {"position": {"x": -2011, "y": -1260, "z": 287}, "ingameTeam": "CT", "playerId": "KRIMZ"}, "victim": {"position": {"x": -1474, "y": -544, "z": 60}, "ingameTeam": "TERRORIST", "playerId": "karrigan"}, "weapon": "ak47", "headshot": false, "penetrated": false}, "roundIdx": 15, "date": "2018-03-04T19:54:26.391+00:00"}, {"type": "kill", "data": {"actor": {"position": {"x": -2004, "y": 832, "z": 480}, "ingameTeam": "CT", "playerId": "KRIMZ"}, "victim": {"position": {"x": -2562, "y": 439, "z": 544}, "ingameTeam": "TERRORIST", "playerId": "GuardiaN"}, "weapon": "ak47", "headshot": false, "penetrated": false}, "roundIdx": 15, "date": "2018-03-04T19:56:02.914+00:00"}], [{"type": "kill", "data": {"actor": {"position": {"x": -574, "y": 23, "z": 4}, "ingameTeam": "TERRORIST", "playerId": "GuardiaN"}, "victim": {"position": {"x": -974, "y": 205, "z": 142}, "ingameTeam": "CT", "playerId": "Golden"}, "weapon": "awp", "headshot": true, "penetrated": false}, "roundIdx": 15, "date": "2018-03-04T19:54:24.239+00:00"}, {"type": "kill", "data": {"actor": {"position": {"x": -660, "y": -62, "z": 18}, "ingameTeam": "TERRORIST", "playerId": "GuardiaN"}, "victim": {"position": {"x": -993, "y": -171, "z": 161}, "ingameTeam": "CT", "playerId": "Lekr0"}, "weapon": "awp", "headshot": false, "penetrated": false}, "roundIdx": 15, "date": "2018-03-04T19:54:28.042+00:00"}], [{"type": "kill", "data": {"actor": {"position": {"x": -469, "y": -1139, "z": 43}, "ingameTeam": "TERRORIST", "playerId": "flusha"}, "victim": {"position": {"x": -609, "y": 165, "z": 73}, "ingameTeam": "CT", "playerId": "NiKo"}, "weapon": "glock", "headshot": true, "penetrated": false}, "roundIdx": 16, "date": "2018-03-04T20:01:03.318+00:00"}, {"type": "kill", "data": {"actor": {"position": {"x": -915, "y": -368, "z": 96}, "ingameTeam": "TERRORIST", "playerId": "flusha"}, "victim": {"position": {"x": -1795, "y": 545, "z": 307}, "ingameTeam": "CT", "playerId": "olofmeister"}, "weapon": "glock", "headshot": true, "penetrated": false}, "roundIdx": 16, "date": "2018-03-04T20:01:36.794+00:00"}], [{"type": "kill", "data": {"actor": {"position": {"x": -1750, "y": 87, "z": 128}, "ingameTeam": "TERRORIST", "playerId": "JW"}, "victim": {"position": {"x": -1423, "y": -76, "z": 179}, "ingameTeam": "CT", "playerId": "rain"}, "weapon": "glock", "headshot": true, "penetrated": false}, "roundIdx": 16, "date": "2018-03-04T20:01:33.443+00:00"}, {"type": "kill", "data": {"actor": {"position": {"x": -1700, "y": 82, "z": 110}, "ingameTeam": "TERRORIST", "playerId": "JW"}, "victim": {"position": {"x": -1517, "y": -16, "z": 192}, "ingameTeam": "CT", "playerId": "GuardiaN"}, "weapon": "glock", "headshot": false, "penetrated": false}, "roundIdx": 16, "date": "2018-03-04T20:01:35.199+00:00"}], [{"type": "kill", "data": {"actor": {"position": {"x": -442, "y": -894, "z": 13}, "ingameTeam": "TERRORIST", "playerId": "flusha"}, "victim": {"position": {"x": -588, "y": -304, "z": 70}, "ingameTeam": "CT", "playerId": "NiKo"}, "weapon": "ak47", "headshot": true, "penetrated": false}, "roundIdx": 19, "date": "2018-03-04T20:06:57.559+00:00"}, {"type": "kill", "data": {"actor": {"position": {"x": -528, "y": -567, "z": 5}, "ingameTeam": "TERRORIST", "playerId": "flusha"}, "victim": {"position": {"x": -552, "y": -279, "z": 62}, "ingameTeam": "CT", "playerId": "olofmeister"}, "weapon": "ak47", "headshot": true, "penetrated": false}, "roundIdx": 19, "date": "2018-03-04T20:07:04.535+00:00"}], [{"type": "kill", "data": {"actor": {"position": {"x": -1061, "y": 491, "z": 85}, "ingameTeam": "TERRORIST", "playerId": "Lekr0"}, "victim": {"position": {"x": -1875, "y": -388, "z": 192}, "ingameTeam": "CT", "playerId": "GuardiaN"}, "weapon": "galilar", "headshot": true, "penetrated": false}, "roundIdx": 19, "date": "2018-03-04T20:07:14.778+00:00"}, {"type": "kill", "data": {"actor": {"position": {"x": -1038, "y": 467, "z": 96}, "ingameTeam": "TERRORIST", "playerId": "Lekr0"}, "victim": {"position": {"x": -1540, "y": 26, "z": 178}, "ingameTeam": "CT", "playerId": "karrigan"}, "weapon": "galilar", "headshot": false, "penetrated": false}, "roundIdx": 19, "date": "2018-03-04T20:07:15.585+00:00"}], [{"type": "kill", "data": {"actor": {"position": {"x": -2321, "y": 387, "z": 480}, "ingameTeam": "TERRORIST", "playerId": "flusha"}, "victim": {"position": {"x": -2558, "y": 1341, "z": 544}, "ingameTeam": "CT", "playerId": "GuardiaN"}, "weapon": "ak47", "headshot": false, "penetrated": false}, "roundIdx": 21, "date": "2018-03-04T20:11:13.285+00:00"}, {"type": "kill", "data": {"actor": {"position": {"x": -2136, "y": 432, "z": 480}, "ingameTeam": "TERRORIST", "playerId": "flusha"}, "victim": {"position": {"x": -2018, "y": 611, "z": 518}, "ingameTeam": "CT", "playerId": "rain"}, "weapon": "ak47", "headshot": true, "penetrated": false}, "roundIdx": 21, "date": "2018-03-04T20:11:15.489+00:00"}], [{"type": "kill", "data": {"actor": {"position": {"x": -380, "y": 294, "z": 21}, "ingameTeam": "TERRORIST", "playerId": "Golden"}, "victim": {"position": {"x": -1077, "y": -199, "z": 163}, "ingameTeam": "CT", "playerId": "karrigan"}, "weapon": "ak47", "headshot": false, "penetrated": false}, "roundIdx": 23, "date": "2018-03-04T20:16:35.223+00:00"}, {"type": "kill", "data": {"actor": {"position": {"x": -748, "y": 90, "z": 62}, "ingameTeam": "TERRORIST", "playerId": "Golden"}, "victim": {"position": {"x": -904, "y": 427, "z": 160}, "ingameTeam": "CT", "playerId": "rain"}, "weapon": "ak47", "headshot": false, "penetrated": false}, "roundIdx": 23, "date": "2018-03-04T20:16:38.347+00:00"}], [{"type": "kill", "data": {"actor": {"position": {"x": -1748, "y": -1778, "z": 96}, "ingameTeam": "TERRORIST", "playerId": "KRIMZ"}, "victim": {"position": {"x": -1794, "y": -968, "z": 152}, "ingameTeam": "CT", "playerId": "olofmeister"}, "weapon": "ak47", "headshot": false, "penetrated": false}, "roundIdx": 23, "date": "2018-03-04T20:16:17.661+00:00"}, {"type": "kill", "data": {"actor": {"position": {"x": -881, "y": -65, "z": 96}, "ingameTeam": "TERRORIST", "playerId": "KRIMZ"}, "victim": {"position": {"x": -1467, "y": 188, "z": 112}, "ingameTeam": "CT", "playerId": "GuardiaN"}, "weapon": "ak47", "headshot": true, "penetrated": true}, "roundIdx": 23, "date": "2018-03-04T20:16:44.706+00:00"}]], "3": [[{"type": "kill", "data": {"actor": {"position": {"x": -1701, "y": -813, "z": 96}, "ingameTeam": "CT", "playerId": "JW"}, "victim": {"position": {"x": -1189, "y": -606, "z": 117}, "ingameTeam": "TERRORIST", "playerId": "GuardiaN"}, "weapon": "mag7", "headshot": true, "penetrated": false}, "roundIdx": 5, "date": "2018-03-04T19:31:39.278+00:00"}, {"type": "kill", "data": {"actor": {"position": {"x": -1251, "y": -917, "z": 10}, "ingameTeam": "CT", "playerId": "JW"}, "victim": {"position": {"x": -822, "y": -968, "z": 89}, "ingameTeam": "TERRORIST", "playerId": "rain"}, "weapon": "mag7", "headshot": false, "penetrated": false}, "roundIdx": 5, "date": "2018-03-04T19:31:50.582+00:00"}, {"type": "kill", "data": {"actor": {"position": {"x": -909, "y": -170, "z": 96}, "ingameTeam": "CT", "playerId": "JW"}, "victim": {"position": {"x": -643, "y": -39, "z": 58}, "ingameTeam": "TERRORIST", "playerId": "NiKo"}, "weapon": "mag7", "headshot": false, "penetrated": false}, "roundIdx": 5, "date": "2018-03-04T19:31:57.451+00:00"}], [{"type": "kill", "data": {"actor": {"position": {"x": -1691, "y": -995, "z": 96}, "ingameTeam": "TERRORIST", "playerId": "rain"}, "victim": {"position": {"x": -1960, "y": -1025, "z": 199}, "ingameTeam": "CT", "playerId": "flusha"}, "weapon": "ak47", "headshot": false, "penetrated": false}, "roundIdx": 12, "date": "2018-03-04T19:46:59.210+00:00"}, {"type": "kill", "data": {"actor": {"position": {"x": -2681, "y": -947, "z": 432}, "ingameTeam": "TERRORIST", "playerId": "rain"}, "victim": {"position": {"x": -2872, "y": -964, "z": 496}, "ingameTeam": "CT", "playerId": "JW"}, "weapon": "ak47", "headshot": true, "penetrated": false}, "roundIdx": 12, "date": "2018-03-04T19:47:44.918+00:00"}, {"type": "kill", "data": {"actor": {"position": {"x": -2052, "y": 575, "z": 514}, "ingameTeam": "TERRORIST", "playerId": "rain"}, "victim": {"position": {"x": -2094, "y": 716, "z": 536}, "ingameTeam": "CT", "playerId": "KRIMZ"}, "weapon": "ak47", "headshot": false, "penetrated": false}, "roundIdx": 12, "date": "2018-03-04T19:48:04.574+00:00"}], [{"type": "kill", "data": {"actor": {"position": {"x": -1126, "y": -629, "z": 83}, "ingameTeam": "TERRORIST", "playerId": "KRIMZ"}, "victim": {"position": {"x": -971, "y": -390, "z": 160}, "ingameTeam": "CT", "playerId": "karrigan"}, "weapon": "ak47", "headshot": false, "penetrated": false}, "roundIdx": 17, "date": "2018-03-04T20:03:31.253+00:00"}, {"type": "kill", "data": {"actor": {"position": {"x": -926, "y": -603, "z": 96}, "ingameTeam": "TERRORIST", "playerId": "KRIMZ"}, "victim": {"position": {"x": -791, "y": 496, "z": 160}, "ingameTeam": "CT", "playerId": "NiKo"}, "weapon": "ak47", "headshot": true, "penetrated": false}, "roundIdx": 17, "date": "2018-03-04T20:03:36.605+00:00"}, {"type": "kill", "data": {"actor": {"position": {"x": -896, "y": -370, "z": 96}, "ingameTeam": "TERRORIST", "playerId": "KRIMZ"}, "victim": {"position": {"x": -1849, "y": -33, "z": 174}, "ingameTeam": "CT", "playerId": "GuardiaN"}, "weapon": "ak47", "headshot": true, "penetrated": false}, "roundIdx": 17, "date": "2018-03-04T20:03:40.377+00:00"}], [{"type": "kill", "data": {"actor": {"position": {"x": -806, "y": -24, "z": 91}, "ingameTeam": "TERRORIST", "playerId": "Lekr0"}, "victim": {"position": {"x": -1050, "y": -639, "z": 142}, "ingameTeam": "CT", "playerId": "olofmeister"}, "weapon": "galilar", "headshot": false, "penetrated": false}, "roundIdx": 18, "date": "2018-03-04T20:04:32.166+00:00"}, {"type": "kill", "data": {"actor": {"position": {"x": -1040, "y": -103, "z": 99}, "ingameTeam": "TERRORIST", "playerId": "Lekr0"}, "victim": {"position": {"x": -1973, "y": 706, "z": 320}, "ingameTeam": "CT", "playerId": "NiKo"}, "weapon": "galilar", "headshot": true, "penetrated": false}, "roundIdx": 18, "date": "2018-03-04T20:04:59.325+00:00"}, {"type": "kill", "data": {"actor": {"position": {"x": -998, "y": -146, "z": 98}, "ingameTeam": "TERRORIST", "playerId": "Lekr0"}, "victim": {"position": {"x": -2003, "y": 697, "z": 320}, "ingameTeam": "CT", "playerId": "rain"}, "weapon": "galilar", "headshot": true, "penetrated": false}, "roundIdx": 18, "date": "2018-03-04T20:05:03.161+00:00"}], [{"type": "kill", "data": {"actor": {"position": {"x": -205, "y": -1053, "z": 22}, "ingameTeam": "TERRORIST", "playerId": "flusha"}, "victim": {"position": {"x": -994, "y": -985, "z": 76}, "ingameTeam": "CT", "playerId": "olofmeister"}, "weapon": "ak47", "headshot": false, "penetrated": false}, "roundIdx": 20, "date": "2018-03-04T20:08:24.909+00:00"}, {"type": "kill", "data": {"actor": {"position": {"x": -3214, "y": -2345, "z": 472}, "ingameTeam": "TERRORIST", "playerId": "flusha"}, "victim": {"position": {"x": -3949, "y": -1314, "z": 577}, "ingameTeam": "CT", "playerId": "rain"}, "weapon": "ak47", "headshot": false, "penetrated": false}, "roundIdx": 20, "date": "2018-03-04T20:09:07.606+00:00"}, {"type": "kill", "data": {"actor": {"position": {"x": -3201, "y": -889, "z": 488}, "ingameTeam": "TERRORIST", "playerId": "flusha"}, "victim": {"position": {"x": -3583, "y": -638, "z": 536}, "ingameTeam": "CT", "playerId": "NiKo"}, "weapon": "ak47", "headshot": true, "penetrated": false}, "roundIdx": 20, "date": "2018-03-04T20:09:20.254+00:00"}], [{"type": "kill", "data": {"actor": {"position": {"x": -3214, "y": -870, "z": 488}, "ingameTeam": "CT", "playerId": "rain"}, "victim": {"position": {"x": -2726, "y": -952, "z": 478}, "ingameTeam": "TERRORIST", "playerId": "Golden"}, "weapon": "deagle", "headshot": true, "penetrated": false}, "roundIdx": 20, "date": "2018-03-04T20:08:45.146+00:00"}, {"type": "kill", "data": {"actor": {"position": {"x": -3285, "y": -819, "z": 488}, "ingameTeam": "CT", "playerId": "rain"}, "victim": {"position": {"x": -2970, "y": -976, "z": 519}, "ingameTeam": "TERRORIST", "playerId": "Lekr0"}, "weapon": "deagle", "headshot": true, "penetrated": false}, "roundIdx": 20, "date": "2018-03-04T20:08:48.763+00:00"}, {"type": "kill", "data": {"actor": {"position": {"x": -3956, "y": -1161, "z": 519}, "ingameTeam": "CT", "playerId": "rain"}, "victim": {"position": {"x": -3864, "y": -1453, "z": 547}, "ingameTeam": "TERRORIST", "playerId": "JW"}, "weapon": "deagle", "headshot": false, "penetrated": false}, "roundIdx": 20, "date": "2018-03-04T20:09:03.222+00:00"}]], "4": [[{"type": "kill", "data": {"actor": {"position": {"x": -1221, "y": -610, "z": 49}, "ingameTeam": "TERRORIST", "playerId": "Lekr0"}, "victim": {"position": {"x": -978, "y": -529, "z": 160}, "ingameTeam": "CT", "playerId": "olofmeister"}, "weapon": "ak47", "headshot": true, "penetrated": false}, "roundIdx": 22, "date": "2018-03-04T20:12:44.363+00:00"}, {"type": "kill", "data": {"actor": {"position": {"x": -1122, "y": -635, "z": 86}, "ingameTeam": "TERRORIST", "playerId": "Lekr0"}, "victim": {"position": {"x": -869, "y": -203, "z": 160}, "ingameTeam": "CT", "playerId": "NiKo"}, "weapon": "ak47", "headshot": false, "penetrated": false}, "roundIdx": 22, "date": "2018-03-04T20:12:46.020+00:00"}, {"type": "kill", "data": {"actor": {"position": {"x": -895, "y": -413, "z": 96}, "ingameTeam": "TERRORIST", "playerId": "Lekr0"}, "victim": {"position": {"x": -1515, "y": -14, "z": 192}, "ingameTeam": "CT", "playerId": "rain"}, "weapon": "ak47", "headshot": false, "penetrated": false}, "roundIdx": 22, "date": "2018-03-04T20:13:31.801+00:00"}, {"type": "kill", "data": {"actor": {"position": {"x": -871, "y": -362, "z": 96}, "ingameTeam": "TERRORIST", "playerId": "Lekr0"}, "victim": {"position": {"x": -1163, "y": -241, "z": 162}, "ingameTeam": "CT", "playerId": "karrigan"}, "weapon": "ak47", "headshot": false, "penetrated": false}, "roundIdx": 22, "date": "2018-03-04T20:13:32.894+00:00"}]], "5": [[{"type": "kill", "data": {"actor": {"position": {"x": -438, "y": -860, "z": 16}, "ingameTeam": "TERRORIST", "playerId": "GuardiaN"}, "victim": {"position": {"x": -685, "y": 278, "z": 94}, "ingameTeam": "CT", "playerId": "flusha"}, "weapon": "awp", "headshot": false, "penetrated": false}, "roundIdx": 9, "date": "2018-03-04T19:39:25.802+00:00"}, {"type": "kill", "data": {"actor": {"position": {"x": -570, "y": -722, "z": 16}, "ingameTeam": "TERRORIST", "playerId": "GuardiaN"}, "victim": {"position": {"x": -485, "y": -494, "z": 76}, "ingameTeam": "CT", "playerId": "JW"}, "weapon": "awp", "headshot": false, "penetrated": false}, "roundIdx": 9, "date": "2018-03-04T19:39:31.520+00:00"}, {"type": "kill", "data": {"actor": {"position": {"x": -547, "y": -694, "z": 17}, "ingameTeam": "TERRORIST", "playerId": "GuardiaN"}, "victim": {"position": {"x": -518, "y": -91, "z": 66}, "ingameTeam": "CT", "playerId": "Lekr0"}, "weapon": "awp", "headshot": true, "penetrated": false}, "roundIdx": 9, "date": "2018-03-04T19:39:33.014+00:00"}, {"type": "kill", "data": {"actor": {"position": {"x": -545, "y": -479, "z": 7}, "ingameTeam": "TERRORIST", "playerId": "GuardiaN"}, "victim": {"position": {"x": -241, "y": 113, "z": 64}, "ingameTeam": "CT", "playerId": "Golden"}, "weapon": "awp", "headshot": false, "penetrated": false}, "roundIdx": 9, "date": "2018-03-04T19:39:40.537+00:00"}, {"type": "kill", "data": {"actor": {"position": {"x": -2612, "y": 1441, "z": 462}, "ingameTeam": "TERRORIST", "playerId": "GuardiaN"}, "victim": {"position": {"x": -2239, "y": 499, "z": 526}, "ingameTeam": "CT", "playerId": "KRIMZ"}, "weapon": "awp", "headshot": true, "penetrated": false}, "roundIdx": 9, "date": "2018-03-04T19:40:56.379+00:00"}]]}